{
	"textures": {
		"0": "animated_java:item/gravity_impaler/gravity_shockwave"
	},
	"elements": [
		{
			"from": [
				-3.6165203164075184,
				18.066758667039586,
				3.9019878432469373
			],
			"to": [
				-3.6165203164075184,
				32,
				12.098012156753063
			],
			"rotation": {
				"angle": -45,
				"axis": "z",
				"origin": [
					-18.369364080718547,
					2.4943124713779454,
					29.30966321511593
				]
			},
			"faces": {
				"north": {
					"uv": [
						0,
						0,
						0,
						4.25
					],
					"texture": "#0"
				},
				"east": {
					"uv": [
						4,
						3.5,
						9,
						16
					],
					"texture": "#0"
				},
				"south": {
					"uv": [
						0,
						0,
						0,
						4.25
					],
					"texture": "#0"
				},
				"west": {
					"uv": [
						9,
						3.75,
						4,
						16
					],
					"texture": "#0"
				},
				"up": {
					"uv": [
						0,
						10.75,
						0,
						0
					],
					"texture": "#0"
				},
				"down": {
					"uv": [
						0,
						0,
						0,
						10.75
					],
					"texture": "#0"
				}
			}
		}
	],
	"display": {
		"head": {
			"rotation": [
				0,
				180,
				0
			]
		}
	}
}