{
	"textures": {
		"1": "animated_java:item/chainsaw/flail"
	},
	"elements": [
		{
			"from": [
				7,
				10.86458,
				-3.0556599999999996
			],
			"to": [
				9,
				12.86458,
				12.94434
			],
			"rotation": {
				"angle": 0,
				"axis": "y",
				"origin": [
					8,
					11.86458,
					4.94434
				]
			},
			"faces": {
				"north": {
					"uv": [
						5,
						8,
						6,
						9
					],
					"texture": "#1"
				},
				"east": {
					"uv": [
						0,
						1,
						8,
						0
					],
					"texture": "#1"
				},
				"south": {
					"uv": [
						6,
						8,
						7,
						9
					],
					"texture": "#1"
				},
				"west": {
					"uv": [
						0,
						1,
						8,
						2
					],
					"texture": "#1"
				},
				"up": {
					"uv": [
						0,
						10,
						1,
						2
					],
					"texture": "#1"
				},
				"down": {
					"uv": [
						2,
						2,
						1,
						10
					],
					"texture": "#1"
				}
			}
		},
		{
			"from": [
				6.9375,
				10.36458,
				-4.68066
			],
			"to": [
				9.0625,
				12.86458,
				-2.1806599999999996
			],
			"rotation": {
				"angle": 45,
				"axis": "x",
				"origin": [
					8,
					11.86458,
					-3.1806599999999996
				]
			},
			"faces": {
				"north": {
					"uv": [
						8,
						0,
						9,
						1.25
					],
					"texture": "#1"
				},
				"east": {
					"uv": [
						7.5,
						5,
						8.75,
						6.25
					],
					"texture": "#1"
				},
				"south": {
					"uv": [
						2,
						8,
						3,
						9.25
					],
					"texture": "#1"
				},
				"west": {
					"uv": [
						7.5,
						6.5,
						8.75,
						7.75
					],
					"texture": "#1"
				},
				"up": {
					"uv": [
						4,
						9.25,
						3,
						8
					],
					"texture": "#1"
				},
				"down": {
					"uv": [
						5,
						8,
						4,
						9.25
					],
					"texture": "#1"
				}
			}
		},
		{
			"from": [
				7,
				10.86458,
				10.75684
			],
			"to": [
				9,
				12.86458,
				10.75684
			],
			"rotation": {
				"angle": 0,
				"axis": "y",
				"origin": [
					8.0625,
					11.86458,
					10.75684
				]
			},
			"faces": {
				"north": {
					"uv": [
						5,
						8,
						6,
						9
					],
					"texture": "#1"
				},
				"east": {
					"uv": [
						0,
						1,
						8,
						0
					],
					"texture": "#1"
				},
				"south": {
					"uv": [
						5,
						8,
						6,
						9
					],
					"texture": "#1"
				},
				"west": {
					"uv": [
						0,
						1,
						0,
						2
					],
					"texture": "#1"
				},
				"up": {
					"uv": [
						0,
						2,
						1,
						2
					],
					"texture": "#1"
				},
				"down": {
					"uv": [
						2,
						2,
						0.984375,
						10
					],
					"texture": "#1"
				}
			}
		}
	],
	"display": {
		"head": {
			"rotation": [
				0,
				180,
				0
			]
		}
	}
}