{
	"textures": {
		"1": "animated_java:item/field_extension/taffy128"
	},
	"elements": [
		{
			"from": [
				5.75,
				1.25,
				5.75
			],
			"to": [
				10.25,
				7,
				10.25
			],
			"rotation": {
				"angle": 0,
				"axis": "y",
				"origin": [
					8,
					4.125,
					8
				]
			},
			"faces": {
				"north": {
					"uv": [
						0,
						5.375,
						0.5,
						6
					],
					"texture": "#1"
				},
				"east": {
					"uv": [
						1.5,
						5.375,
						2,
						6
					],
					"texture": "#1"
				},
				"south": {
					"uv": [
						0.5,
						5.375,
						1,
						6
					],
					"texture": "#1"
				},
				"west": {
					"uv": [
						1,
						5.375,
						1.5,
						6
					],
					"texture": "#1"
				},
				"up": {
					"uv": [
						0.5,
						4.5,
						0,
						4
					],
					"texture": "#1"
				},
				"down": {
					"uv": [
						1,
						4,
						0.5,
						4.5
					],
					"texture": "#1"
				}
			}
		},
		{
			"from": [
				6.025,
				7.475,
				8.025
			],
			"to": [
				9.975,
				7.699999999999999,
				9.075
			],
			"rotation": {
				"angle": -45,
				"axis": "x",
				"origin": [
					8,
					8.7,
					7.699999999999999
				]
			},
			"faces": {
				"north": {
					"uv": [
						4.08718,
						2.57602,
						4.31744,
						2.67906
					],
					"texture": "#1"
				},
				"east": {
					"uv": [
						4.2023,
						5.77028,
						4.25986,
						5.87332
					],
					"texture": "#1"
				},
				"south": {
					"uv": [
						4.08718,
						2.67906,
						4.31744,
						2.7821
					],
					"texture": "#1"
				},
				"west": {
					"uv": [
						3.28126,
						7.52196,
						3.33882,
						7.625
					],
					"texture": "#1"
				},
				"up": {
					"uv": [
						4.31744,
						2.88514,
						4.08718,
						2.7821
					],
					"texture": "#1"
				},
				"down": {
					"uv": [
						1.8421,
						7.31588,
						1.61184,
						7.41892
					],
					"texture": "#1"
				}
			}
		},
		{
			"from": [
				6.025,
				7.05,
				8.775
			],
			"to": [
				9.975,
				7.775,
				9.51
			],
			"rotation": {
				"angle": -22.5,
				"axis": "x",
				"origin": [
					8,
					8.7,
					7.699999999999999
				]
			},
			"faces": {
				"north": {
					"uv": [
						4.08718,
						2.88514,
						4.31744,
						2.98818
					],
					"texture": "#1"
				},
				"east": {
					"uv": [
						4.2023,
						5.87332,
						4.25986,
						5.97636
					],
					"texture": "#1"
				},
				"south": {
					"uv": [
						4.08718,
						2.98818,
						4.31744,
						3.09122
					],
					"texture": "#1"
				},
				"west": {
					"uv": [
						3.33882,
						7.52196,
						3.39638,
						7.625
					],
					"texture": "#1"
				},
				"up": {
					"uv": [
						4.31744,
						3.19426,
						4.08718,
						3.09122
					],
					"texture": "#1"
				},
				"down": {
					"uv": [
						4.31744,
						3.19426,
						4.08718,
						3.2973
					],
					"texture": "#1"
				}
			}
		},
		{
			"from": [
				6.025,
				7.324999999999999,
				8.475
			],
			"to": [
				9.975,
				7.675000000000001,
				9.21
			],
			"rotation": {
				"angle": -45,
				"axis": "x",
				"origin": [
					8,
					8.7,
					7.699999999999999
				]
			},
			"faces": {
				"north": {
					"uv": [
						1.8421,
						7.31588,
						2.07236,
						7.41892
					],
					"texture": "#1"
				},
				"east": {
					"uv": [
						4.2023,
						5.97636,
						4.25986,
						6.0794
					],
					"texture": "#1"
				},
				"south": {
					"uv": [
						4.08718,
						3.2973,
						4.31744,
						3.40034
					],
					"texture": "#1"
				},
				"west": {
					"uv": [
						3.39638,
						7.52196,
						3.45394,
						7.625
					],
					"texture": "#1"
				},
				"up": {
					"uv": [
						4.31744,
						3.50338,
						4.08718,
						3.40034
					],
					"texture": "#1"
				},
				"down": {
					"uv": [
						2.30264,
						7.31588,
						2.07236,
						7.41892
					],
					"texture": "#1"
				}
			}
		},
		{
			"from": [
				6.025,
				7.5,
				6
			],
			"to": [
				9.975,
				7.875,
				10
			],
			"rotation": {
				"angle": 0,
				"axis": "y",
				"origin": [
					8,
					8.7,
					7.75
				]
			},
			"faces": {
				"north": {
					"uv": [
						3.05264,
						7.89696,
						3.2829,
						8
					],
					"texture": "#1"
				},
				"east": {
					"uv": [
						3.2829,
						7.89696,
						3.51316,
						8
					],
					"texture": "#1"
				},
				"south": {
					"uv": [
						3.51316,
						7.89696,
						3.74342,
						8
					],
					"texture": "#1"
				},
				"west": {
					"uv": [
						3.74342,
						7.89696,
						3.97368,
						8
					],
					"texture": "#1"
				},
				"up": {
					"uv": [
						4.49178,
						2.6419,
						4.26152,
						2.22974
					],
					"texture": "#1"
				},
				"down": {
					"uv": [
						2.13158,
						6.86656,
						1.90132,
						7.27872
					],
					"texture": "#1"
				}
			}
		},
		{
			"from": [
				6.025,
				7.5,
				6.550000000000001
			],
			"to": [
				6.025,
				8.875,
				9.45
			],
			"rotation": {
				"angle": 0,
				"axis": "y",
				"origin": [
					8,
					8.7,
					7.75
				]
			},
			"faces": {
				"north": {
					"uv": [
						0,
						0,
						0,
						0.10304
					],
					"texture": "#1"
				},
				"east": {
					"uv": [
						4.14474,
						4.73986,
						4.31744,
						4.8429
					],
					"texture": "#1"
				},
				"south": {
					"uv": [
						0,
						0,
						0,
						0.10304
					],
					"texture": "#1"
				},
				"west": {
					"uv": [
						2.7056,
						7.41892,
						2.8783,
						7.52196
					],
					"texture": "#1"
				},
				"up": {
					"uv": [
						0,
						0.30912,
						0,
						0
					],
					"texture": "#1"
				},
				"down": {
					"uv": [
						0,
						0,
						0,
						0.30912
					],
					"texture": "#1"
				}
			}
		},
		{
			"from": [
				6.025,
				8.875,
				6.899999999999999
			],
			"to": [
				6.025,
				9.2,
				8.95
			],
			"rotation": {
				"angle": 0,
				"axis": "y",
				"origin": [
					8,
					8.7,
					7.75
				]
			},
			"faces": {
				"north": {
					"uv": [
						0,
						0,
						0,
						0.10304
					],
					"texture": "#1"
				},
				"east": {
					"uv": [
						4.14474,
						5.3581,
						4.25986,
						5.46114
					],
					"texture": "#1"
				},
				"south": {
					"uv": [
						0,
						0,
						0,
						0.10304
					],
					"texture": "#1"
				},
				"west": {
					"uv": [
						4.14474,
						5.46114,
						4.25986,
						5.5642
					],
					"texture": "#1"
				},
				"up": {
					"uv": [
						0,
						0.20608,
						0,
						0
					],
					"texture": "#1"
				},
				"down": {
					"uv": [
						0,
						0,
						0,
						0.20608
					],
					"texture": "#1"
				}
			}
		},
		{
			"from": [
				10,
				8.875,
				6.899999999999999
			],
			"to": [
				10,
				9.2,
				8.95
			],
			"rotation": {
				"angle": 0,
				"axis": "y",
				"origin": [
					8,
					8.7,
					7.75
				]
			},
			"faces": {
				"north": {
					"uv": [
						0,
						0,
						0,
						0.10304
					],
					"texture": "#1"
				},
				"east": {
					"uv": [
						3.10856,
						7.41892,
						3.22368,
						7.52196
					],
					"texture": "#1"
				},
				"south": {
					"uv": [
						0,
						0,
						0,
						0.10304
					],
					"texture": "#1"
				},
				"west": {
					"uv": [
						4.14474,
						5.5642,
						4.25986,
						5.66724
					],
					"texture": "#1"
				},
				"up": {
					"uv": [
						0,
						0.20608,
						0,
						0
					],
					"texture": "#1"
				},
				"down": {
					"uv": [
						0,
						0,
						0,
						0.20608
					],
					"texture": "#1"
				}
			}
		},
		{
			"from": [
				10,
				7.5,
				6.550000000000001
			],
			"to": [
				10,
				8.875,
				9.45
			],
			"rotation": {
				"angle": 0,
				"axis": "y",
				"origin": [
					8,
					8.7,
					7.75
				]
			},
			"faces": {
				"north": {
					"uv": [
						0,
						0,
						0,
						0.10304
					],
					"texture": "#1"
				},
				"east": {
					"uv": [
						4.14474,
						4.8429,
						4.31744,
						4.94594
					],
					"texture": "#1"
				},
				"south": {
					"uv": [
						0,
						0,
						0,
						0.10304
					],
					"texture": "#1"
				},
				"west": {
					"uv": [
						4.14474,
						4.94594,
						4.31744,
						5.04898
					],
					"texture": "#1"
				},
				"up": {
					"uv": [
						0,
						0.30912,
						0,
						0
					],
					"texture": "#1"
				},
				"down": {
					"uv": [
						0,
						0,
						0,
						0.30912
					],
					"texture": "#1"
				}
			}
		},
		{
			"from": [
				6.025,
				7.375,
				7.850000000000001
			],
			"to": [
				9.975,
				8.225,
				8.775
			],
			"rotation": {
				"angle": -45,
				"axis": "x",
				"origin": [
					8,
					8.7,
					7.699999999999999
				]
			},
			"faces": {
				"north": {
					"uv": [
						3.22368,
						7.31588,
						3.45394,
						7.41892
					],
					"texture": "#1"
				},
				"east": {
					"uv": [
						4.2023,
						6.0794,
						4.25986,
						6.18244
					],
					"texture": "#1"
				},
				"south": {
					"uv": [
						3.45394,
						7.31588,
						3.68422,
						7.41892
					],
					"texture": "#1"
				},
				"west": {
					"uv": [
						3.45394,
						7.52196,
						3.51152,
						7.625
					],
					"texture": "#1"
				},
				"up": {
					"uv": [
						3.91448,
						7.41892,
						3.68422,
						7.31588
					],
					"texture": "#1"
				},
				"down": {
					"uv": [
						4.14474,
						7.31588,
						3.91448,
						7.41892
					],
					"texture": "#1"
				}
			}
		},
		{
			"from": [
				6.025,
				7.875,
				8.1
			],
			"to": [
				9.975,
				8.6,
				8.55
			],
			"rotation": {
				"angle": -45,
				"axis": "x",
				"origin": [
					8,
					8.7,
					7.699999999999999
				]
			},
			"faces": {
				"north": {
					"uv": [
						0,
						7.41892,
						0.23026,
						7.52196
					],
					"texture": "#1"
				},
				"east": {
					"uv": [
						4.2023,
						6.18244,
						4.25986,
						6.28548
					],
					"texture": "#1"
				},
				"south": {
					"uv": [
						0.23026,
						7.41892,
						0.46052,
						7.52196
					],
					"texture": "#1"
				},
				"west": {
					"uv": [
						3.51152,
						7.52196,
						3.56908,
						7.625
					],
					"texture": "#1"
				},
				"up": {
					"uv": [
						0.6908,
						7.52196,
						0.46052,
						7.41892
					],
					"texture": "#1"
				},
				"down": {
					"uv": [
						0.92106,
						7.41892,
						0.6908,
						7.52196
					],
					"texture": "#1"
				}
			}
		},
		{
			"from": [
				6.025,
				8.3,
				8.025
			],
			"to": [
				9.975,
				8.75,
				8.465
			],
			"rotation": {
				"angle": -45,
				"axis": "x",
				"origin": [
					8,
					8.7,
					7.699999999999999
				]
			},
			"faces": {
				"north": {
					"uv": [
						0.92106,
						7.41892,
						1.15132,
						7.52196
					],
					"texture": "#1"
				},
				"east": {
					"uv": [
						4.2023,
						6.28548,
						4.25986,
						6.38852
					],
					"texture": "#1"
				},
				"south": {
					"uv": [
						1.15132,
						7.41892,
						1.38158,
						7.52196
					],
					"texture": "#1"
				},
				"west": {
					"uv": [
						3.56908,
						7.52196,
						3.62664,
						7.625
					],
					"texture": "#1"
				},
				"up": {
					"uv": [
						1.61184,
						7.52196,
						1.38158,
						7.41892
					],
					"texture": "#1"
				},
				"down": {
					"uv": [
						1.8421,
						7.41892,
						1.61184,
						7.52196
					],
					"texture": "#1"
				}
			}
		},
		{
			"from": [
				6.025,
				8.65,
				8.025
			],
			"to": [
				9.975,
				9.3,
				8.465
			],
			"rotation": {
				"angle": -45,
				"axis": "x",
				"origin": [
					8,
					8.7,
					7.699999999999999
				]
			},
			"faces": {
				"north": {
					"uv": [
						1.8421,
						7.41892,
						2.07236,
						7.52196
					],
					"texture": "#1"
				},
				"east": {
					"uv": [
						4.2023,
						6.38852,
						4.25986,
						6.49156
					],
					"texture": "#1"
				},
				"south": {
					"uv": [
						4.14474,
						3.50338,
						4.375,
						3.60642
					],
					"texture": "#1"
				},
				"west": {
					"uv": [
						3.62664,
						7.52196,
						3.68422,
						7.625
					],
					"texture": "#1"
				},
				"up": {
					"uv": [
						4.375,
						3.70946,
						4.14474,
						3.60642
					],
					"texture": "#1"
				},
				"down": {
					"uv": [
						2.30264,
						7.41892,
						2.07236,
						7.52196
					],
					"texture": "#1"
				}
			}
		},
		{
			"from": [
				6.025,
				8.84,
				8.225
			],
			"to": [
				9.975,
				9.815,
				8.665
			],
			"rotation": {
				"angle": -45,
				"axis": "x",
				"origin": [
					8,
					8.7,
					7.699999999999999
				]
			},
			"faces": {
				"north": {
					"uv": [
						4.14474,
						3.70946,
						4.375,
						3.8125
					],
					"texture": "#1"
				},
				"east": {
					"uv": [
						4.2023,
						6.49156,
						4.25986,
						6.5946
					],
					"texture": "#1"
				},
				"south": {
					"uv": [
						4.14474,
						3.8125,
						4.375,
						3.91554
					],
					"texture": "#1"
				},
				"west": {
					"uv": [
						3.68422,
						7.52196,
						3.74178,
						7.625
					],
					"texture": "#1"
				},
				"up": {
					"uv": [
						4.375,
						4.01858,
						4.14474,
						3.91554
					],
					"texture": "#1"
				},
				"down": {
					"uv": [
						4.375,
						4.01858,
						4.14474,
						4.12162
					],
					"texture": "#1"
				}
			}
		},
		{
			"from": [
				6.025,
				9.29,
				8.5
			],
			"to": [
				9.975,
				10.065,
				9.05
			],
			"rotation": {
				"angle": -45,
				"axis": "x",
				"origin": [
					8,
					8.7,
					7.699999999999999
				]
			},
			"faces": {
				"north": {
					"uv": [
						2.30264,
						7.41892,
						2.5329,
						7.52196
					],
					"texture": "#1"
				},
				"east": {
					"uv": [
						4.2023,
						6.5946,
						4.25986,
						6.69764
					],
					"texture": "#1"
				},
				"south": {
					"uv": [
						4.14474,
						4.12162,
						4.375,
						4.22466
					],
					"texture": "#1"
				},
				"west": {
					"uv": [
						3.74178,
						7.52196,
						3.79934,
						7.625
					],
					"texture": "#1"
				},
				"up": {
					"uv": [
						4.375,
						4.3277,
						4.14474,
						4.22466
					],
					"texture": "#1"
				},
				"down": {
					"uv": [
						4.375,
						4.3277,
						4.14474,
						4.43074
					],
					"texture": "#1"
				}
			}
		},
		{
			"from": [
				6,
				1.5,
				6
			],
			"to": [
				10,
				7.5,
				10
			],
			"rotation": {
				"angle": 0,
				"axis": "y",
				"origin": [
					10,
					1.5,
					8
				]
			},
			"faces": {
				"north": {
					"uv": [
						3.5,
						7.25,
						4,
						8
					],
					"texture": "#1"
				},
				"east": {
					"uv": [
						3,
						7.25,
						3.5,
						8
					],
					"texture": "#1"
				},
				"south": {
					"uv": [
						2.5,
						7.25,
						3,
						8
					],
					"texture": "#1"
				},
				"west": {
					"uv": [
						2,
						7.25,
						2.5,
						8
					],
					"texture": "#1"
				},
				"up": {
					"uv": [
						0.5,
						8.25,
						0,
						7.75
					],
					"texture": "#1"
				},
				"down": {
					"uv": [
						3.5,
						6,
						3,
						6.5
					],
					"texture": "#1"
				}
			}
		}
	],
	"display": {
		"head": {
			"rotation": [
				0,
				180,
				0
			]
		}
	}
}