{
	"textures": {
		"0": "animated_java:item/purple_fire/purple_fire"
	},
	"elements": [
		{
			"from": [
				7.5,
				7.5,
				7.5
			],
			"to": [
				8.5,
				8.5,
				8.5
			],
			"rotation": {
				"angle": 0,
				"axis": "y",
				"origin": [
					9,
					9,
					9
				]
			},
			"faces": {
				"north": {
					"uv": [
						1.25,
						11.5,
						1.5,
						11.75
					],
					"texture": "#0"
				},
				"east": {
					"uv": [
						11.5,
						1.25,
						11.75,
						1.5
					],
					"texture": "#0"
				},
				"south": {
					"uv": [
						1.5,
						11.5,
						1.75,
						11.75
					],
					"texture": "#0"
				},
				"west": {
					"uv": [
						11.5,
						1.5,
						11.75,
						1.75
					],
					"texture": "#0"
				},
				"up": {
					"uv": [
						2,
						11.75,
						1.75,
						11.5
					],
					"texture": "#0"
				},
				"down": {
					"uv": [
						11.75,
						1.75,
						11.5,
						2
					],
					"texture": "#0"
				}
			}
		}
	],
	"display": {
		"head": {
			"rotation": [
				0,
				180,
				0
			]
		}
	}
}