{
	"textures": {
		"0": "animated_java:item/zamor_ice_storm/zamor_ice_storm"
	},
	"elements": [
		{
			"from": [
				-4,
				6.9186046511627906,
				-4
			],
			"to": [
				20,
				10.755813953488373,
				20
			],
			"rotation": {
				"angle": 0,
				"axis": "y",
				"origin": [
					8,
					8.348837209302326,
					8
				]
			},
			"faces": {
				"north": {
					"uv": [
						7.75,
						3.875,
						10.375,
						4.375
					],
					"texture": "#0"
				},
				"east": {
					"uv": [
						7.75,
						4.375,
						10.375,
						4.875
					],
					"texture": "#0"
				},
				"south": {
					"uv": [
						2.375,
						8.25,
						5,
						8.75
					],
					"texture": "#0"
				},
				"west": {
					"uv": [
						2.375,
						8.75,
						5,
						9.25
					],
					"texture": "#0"
				},
				"up": {
					"uv": [
						5.25,
						2.625,
						2.625,
						0
					],
					"texture": "#0"
				},
				"down": {
					"uv": [
						5.25,
						2.625,
						2.625,
						5.25
					],
					"texture": "#0"
				}
			}
		}
	],
	"display": {
		"head": {
			"rotation": [
				0,
				180,
				0
			]
		}
	}
}